sedo/__init__.py
sedo/base.py
sedo/optimizer.py
sedo/particle.py
sedo/search.py
sedo/utils.py
sedo-1.2.5.dist-info/LICENSE
sedo-1.2.5.dist-info/METADATA
sedo-1.2.5.dist-info/WHEEL
sedo-1.2.5.dist-info/top_level.txt
sedo-1.2.5.dist-info/RECORD
